pxctl/__init__.py
pxctl/layout.py
pxctl/notifications.py
pxctl/printer.py
pxctl/pxctl.py
pxctl-0.0.3.dist-info/METADATA
pxctl-0.0.3.dist-info/WHEEL
pxctl-0.0.3.dist-info/entry_points.txt
pxctl-0.0.3.dist-info/licenses/LICENSE
pxctl-0.0.3.dist-info/RECORD
