Metadata-Version: 2.1
Name: pxctl
Version: 0.0.3
Summary: Command line tool for Picaso Designer X PRO
Project-URL: Homepage, https://github.com/olegh/pxctl
Project-URL: Issues, https://github.com/olegh/pxctl/issues
Author-email: Oleg Khretinin <snail.incm@gmail.com>
License-File: LICENSE
Classifier: License :: OSI Approved :: MIT License
Classifier: Operating System :: POSIX
Classifier: Programming Language :: Python :: 3
Requires-Python: >=3.7
Requires-Dist: tabulate
